[
  {
    "index": 1,
    "item_id": "MOHINF9PII4Y9",
    "name": "Flow - 4月28日 0146",
    "ext": "png",
    "file_path": "D:\\杂项\\素材.library\\images\\MOHINF9PII4Y9.info\\Flow - 4月28日 0146.png",
    "existing_tags": [],
    "modificationTime": 1777313637133
  },
  {
    "index": 2,
    "item_id": "MOHI9WGS8GJ5T",
    "name": "白色背景替换成图二类似的网格，然后图片中的英文字母全部替换成简约的构成衬线，或者网点等符合原图风格的某种构成元素_2K_202604280203",
    "ext": "jpg",
    "file_path": "D:\\杂项\\素材.library\\images\\MOHI9WGS8GJ5T.info\\白色背景替换成图二类似的网格，然后图片中的英文字母全部替换成简约的构成衬线，或者网点等符合原图风格的某种构成元素_2K_202604280203.jpg",
    "existing_tags": [],
    "modificationTime": 1777313006234
  },
  {
    "index": 3,
    "item_id": "MOHHTKZXPSU03",
    "name": "Flow - 4月28日 0146",
    "ext": "png",
    "file_path": "D:\\杂项\\素材.library\\images\\MOHHTKZXPSU03.info\\Flow - 4月28日 0146.png",
    "existing_tags": [],
    "modificationTime": 1777312244877
  },
  {
    "index": 4,
    "item_id": "MOHGCK4MIWUWJ",
    "name": "Flow - 4月20日 0017",
    "ext": "png",
    "file_path": "D:\\杂项\\素材.library\\images\\MOHGCK4MIWUWJ.info\\Flow - 4月20日 0017.png",
    "existing_tags": [],
    "modificationTime": 1777309770982
  },
  {
    "index": 5,
    "item_id": "MOHG56Q73FVLG",
    "name": "Flow - 4月20日 0017",
    "ext": "png",
    "file_path": "D:\\杂项\\素材.library\\images\\MOHG56Q73FVLG.info\\Flow - 4月20日 0017.png",
    "existing_tags": [],
    "modificationTime": 1777309427023
  },
  {
    "index": 6,
    "item_id": "MOHG3S649OEL8",
    "name": "Flow - 4月20日 0017",
    "ext": "png",
    "file_path": "D:\\杂项\\素材.library\\images\\MOHG3S649OEL8.info\\Flow - 4月20日 0017.png",
    "existing_tags": [],
    "modificationTime": 1777309361500
  },
  {
    "index": 7,
    "item_id": "MOHFW7Y7QUM11",
    "name": "Flow - 4月20日 0017",
    "ext": "png",
    "file_path": "D:\\杂项\\素材.library\\images\\MOHFW7Y7QUM11.info\\Flow - 4月20日 0017.png",
    "existing_tags": [],
    "modificationTime": 1777309008703
  },
  {
    "index": 8,
    "item_id": "MOHDBZE4AVX7U",
    "name": "takamatsu!",
    "ext": "png",
    "file_path": "D:\\杂项\\素材.library\\images\\MOHDBZE4AVX7U.info\\takamatsu!.png",
    "existing_tags": [],
    "modificationTime": 1777304705260
  },
  {
    "index": 9,
    "item_id": "MOHDAHY25Z4GX",
    "name": "CubeSat Kit Modules",
    "ext": "jpg",
    "file_path": "D:\\杂项\\素材.library\\images\\MOHDAHY25Z4GX.info\\CubeSat Kit Modules.jpg",
    "existing_tags": [],
    "modificationTime": 1777304635994
  },
  {
    "index": 10,
    "item_id": "MOHD9OL7PVYNM",
    "name": "收藏到 cidade",
    "ext": "jpg",
    "file_path": "D:\\杂项\\素材.library\\images\\MOHD9OL7PVYNM.info\\收藏到 cidade.jpg",
    "existing_tags": [],
    "modificationTime": 1777304597947
  },
  {
    "index": 11,
    "item_id": "MOHD971OXSS4G",
    "name": "收藏到 你创建的 Pin 图",
    "ext": "jpg",
    "file_path": "D:\\杂项\\素材.library\\images\\MOHD971OXSS4G.info\\收藏到 你创建的 Pin 图.jpg",
    "existing_tags": [],
    "modificationTime": 1777304575213
  },
  {
    "index": 12,
    "item_id": "MOHBRM2H61VRU",
    "name": "收藏到 靈感の瞬間",
    "ext": "jpg",
    "file_path": "D:\\杂项\\素材.library\\images\\MOHBRM2H61VRU.info\\收藏到 靈感の瞬間.jpg",
    "existing_tags": [],
    "modificationTime": 1777302075257
  },
  {
    "index": 13,
    "item_id": "MOHBRKES8TY65",
    "name": "收藏到 靈感の瞬間",
    "ext": "jpg",
    "file_path": "D:\\杂项\\素材.library\\images\\MOHBRKES8TY65.info\\收藏到 靈感の瞬間.jpg",
    "existing_tags": [],
    "modificationTime": 1777302073108
  },
  {
    "index": 14,
    "item_id": "MOHBQ0BRU33SW",
    "name": "收藏到  INSPIRATIONAL  ABSTRACT",
    "ext": "png",
    "file_path": "D:\\杂项\\素材.library\\images\\MOHBQ0BRU33SW.info\\收藏到  INSPIRATIONAL  ABSTRACT.png",
    "existing_tags": [],
    "modificationTime": 1777302000423
  },
  {
    "index": 15,
    "item_id": "MOHBOYF137WM7",
    "name": "收藏到 服",
    "ext": "jpg",
    "file_path": "D:\\杂项\\素材.library\\images\\MOHBOYF137WM7.info\\收藏到 服.jpg",
    "existing_tags": [],
    "modificationTime": 1777301951293
  },
  {
    "index": 16,
    "item_id": "MOHBOMNFP47G9",
    "name": "收藏到 RELML",
    "ext": "jpg",
    "file_path": "D:\\杂项\\素材.library\\images\\MOHBOMNFP47G9.info\\收藏到 RELML.jpg",
    "existing_tags": [],
    "modificationTime": 1777301936043
  },
  {
    "index": 17,
    "item_id": "MOHBNHAC9CO52",
    "name": "X",
    "ext": "jpg",
    "file_path": "D:\\杂项\\素材.library\\images\\MOHBNHAC9CO52.info\\X.jpg",
    "existing_tags": [],
    "modificationTime": 1777301882436
  },
  {
    "index": 18,
    "item_id": "MOHBD0CA7PBKZ",
    "name": "收藏到 ULTIMATE character references",
    "ext": "jpg",
    "file_path": "D:\\杂项\\素材.library\\images\\MOHBD0CA7PBKZ.info\\收藏到 ULTIMATE character references.jpg",
    "existing_tags": [],
    "modificationTime": 1777301393914
  },
  {
    "index": 19,
    "item_id": "MOH9OQQXM3TOU",
    "name": "FELO Unveils a Modern Take On Hondas Cult Classic Motocompo With the F",
    "ext": "png",
    "file_path": "D:\\杂项\\素材.library\\images\\MOH9OQQXM3TOU.info\\FELO Unveils a Modern Take On Hondas Cult Classic Motocompo With the F.png",
    "existing_tags": [],
    "modificationTime": 1777298582121
  },
  {
    "index": 20,
    "item_id": "MOH9O12F905OG",
    "name": "하가우 (@___hg6) on X",
    "ext": "png",
    "file_path": "D:\\杂项\\素材.library\\images\\MOH9O12F905OG.info\\하가우 (@___hg6) on X.png",
    "existing_tags": [],
    "modificationTime": 1777298548840
  }
]