[
  {
    "index": 1,
    "item_id": "MMQ7IYB6SPH3X",
    "name": "收藏到 Sci-fiSpaceshipsMechs",
    "ext": "jpg",
    "file_path": "D:\\杂项\\素材.library\\images\\MMQ7IYB6SPH3X.info\\收藏到 Sci-fiSpaceshipsMechs.jpg",
    "existing_tags": [],
    "modificationTime": 1773485583666
  },
  {
    "index": 2,
    "item_id": "MMQ7IBJ4VE8CV",
    "name": "MAD FUEL 01.Lighter , i H i",
    "ext": "jpg",
    "file_path": "D:\\杂项\\素材.library\\images\\MMQ7IBJ4VE8CV.info\\MAD FUEL 01.Lighter , i H i.jpg",
    "existing_tags": [],
    "modificationTime": 1773485554144
  },
  {
    "index": 3,
    "item_id": "MMPVCCYC2U6CM",
    "name": "ОТК-008 24.06, Andrew Zinchenko",
    "ext": "jpg",
    "file_path": "D:\\杂项\\素材.library\\images\\MMPVCCYC2U6CM.info\\ОТК-008 24.06, Andrew Zinchenko.jpg",
    "existing_tags": [],
    "modificationTime": 1773465120660
  },
  {
    "index": 4,
    "item_id": "MMPUEYN8DANTN",
    "name": "MAD FUEL 01.Lighter , i H i @ArtStation",
    "ext": "jpg",
    "file_path": "D:\\杂项\\素材.library\\images\\MMPUEYN8DANTN.info\\MAD FUEL 01.Lighter , i H i @ArtStation.jpg",
    "existing_tags": [],
    "modificationTime": 1773463562468
  },
  {
    "index": 5,
    "item_id": "MMPUEKPYWBCVJ",
    "name": "@ArtStation",
    "ext": "jpg",
    "file_path": "D:\\杂项\\素材.library\\images\\MMPUEKPYWBCVJ.info\\@ArtStation.jpg",
    "existing_tags": [],
    "modificationTime": 1773463544422
  },
  {
    "index": 6,
    "item_id": "MMPU93LSCW2P9",
    "name": "收藏到 device",
    "ext": "jpg",
    "file_path": "D:\\杂项\\素材.library\\images\\MMPU93LSCW2P9.info\\收藏到 device.jpg",
    "existing_tags": [],
    "modificationTime": 1773463288961
  },
  {
    "index": 7,
    "item_id": "MMOFZMYPJYQZU",
    "name": "收藏到 Gear",
    "ext": "png",
    "file_path": "D:\\杂项\\素材.library\\images\\MMOFZMYPJYQZU.info\\收藏到 Gear.png",
    "existing_tags": [],
    "modificationTime": 1773378866689
  },
  {
    "index": 8,
    "item_id": "MMNQFMY2M12LB",
    "name": "收藏到 01_Design reference",
    "ext": "jpg",
    "file_path": "D:\\杂项\\素材.library\\images\\MMNQFMY2M12LB.info\\收藏到 01_Design reference.jpg",
    "existing_tags": [],
    "modificationTime": 1773335943146
  },
  {
    "index": 9,
    "item_id": "MMNQF1GL6TGOL",
    "name": "收藏到 Sketch",
    "ext": "jpg",
    "file_path": "D:\\杂项\\素材.library\\images\\MMNQF1GL6TGOL.info\\收藏到 Sketch.jpg",
    "existing_tags": [],
    "modificationTime": 1773335915301
  },
  {
    "index": 10,
    "item_id": "MMNQE0UWWV4H2",
    "name": "收藏到 Sketch",
    "ext": "jpg",
    "file_path": "D:\\杂项\\素材.library\\images\\MMNQE0UWWV4H2.info\\收藏到 Sketch.jpg",
    "existing_tags": [],
    "modificationTime": 1773335867864
  },
  {
    "index": 11,
    "item_id": "MMNQDWX45GPZT",
    "name": "收藏到 GrphkDesign",
    "ext": "jpg",
    "file_path": "D:\\杂项\\素材.library\\images\\MMNQDWX45GPZT.info\\收藏到 GrphkDesign.jpg",
    "existing_tags": [],
    "modificationTime": 1773335862760
  },
  {
    "index": 12,
    "item_id": "MMNQD351SHFRA",
    "name": "收藏到 GrphkDesign",
    "ext": "jpg",
    "file_path": "D:\\杂项\\素材.library\\images\\MMNQD351SHFRA.info\\收藏到 GrphkDesign.jpg",
    "existing_tags": [],
    "modificationTime": 1773335824165
  },
  {
    "index": 13,
    "item_id": "MMNQCX5O6Y9F2",
    "name": "收藏到 GrphkDesign",
    "ext": "jpg",
    "file_path": "D:\\杂项\\素材.library\\images\\MMNQCX5O6Y9F2.info\\收藏到 GrphkDesign.jpg",
    "existing_tags": [],
    "modificationTime": 1773335816412
  },
  {
    "index": 14,
    "item_id": "MMNQCV5D2XBF2",
    "name": "收藏到 GrphkDesign",
    "ext": "png",
    "file_path": "D:\\杂项\\素材.library\\images\\MMNQCV5D2XBF2.info\\收藏到 GrphkDesign.png",
    "existing_tags": [],
    "modificationTime": 1773335813812
  },
  {
    "index": 15,
    "item_id": "MMNPXKT9DRWKH",
    "name": "收藏到 GrphkDesign",
    "ext": "jpg",
    "file_path": "D:\\杂项\\素材.library\\images\\MMNPXKT9DRWKH.info\\收藏到 GrphkDesign.jpg",
    "existing_tags": [],
    "modificationTime": 1773335100573
  },
  {
    "index": 16,
    "item_id": "MMNPWXQDVWDQQ",
    "name": "收藏到 Product Design",
    "ext": "jpg",
    "file_path": "D:\\杂项\\素材.library\\images\\MMNPWXQDVWDQQ.info\\收藏到 Product Design.jpg",
    "existing_tags": [],
    "modificationTime": 1773335070661
  },
  {
    "index": 17,
    "item_id": "MMNPWH63K6FFT",
    "name": "其中包括图片：",
    "ext": "png",
    "file_path": "D:\\杂项\\素材.library\\images\\MMNPWH63K6FFT.info\\其中包括图片：.png",
    "existing_tags": [],
    "modificationTime": 1773335049195
  },
  {
    "index": 18,
    "item_id": "MMNPWBQWYP878",
    "name": "Utilitarian MechTank Decals Etsy",
    "ext": "jpg",
    "file_path": "D:\\杂项\\素材.library\\images\\MMNPWBQWYP878.info\\Utilitarian MechTank Decals Etsy.jpg",
    "existing_tags": [],
    "modificationTime": 1773335042168
  },
  {
    "index": 19,
    "item_id": "MMNPWANQMXGV3",
    "name": "SVG Cyberpunk Poster - Digital Download Print Modern Poster Wall Art E",
    "ext": "jpg",
    "file_path": "D:\\杂项\\素材.library\\images\\MMNPWANQMXGV3.info\\SVG Cyberpunk Poster - Digital Download Print Modern Poster Wall Art E.jpg",
    "existing_tags": [],
    "modificationTime": 1773335040758
  },
  {
    "index": 20,
    "item_id": "MMNPVYKJO2R8T",
    "name": "其中包括图片：",
    "ext": "png",
    "file_path": "D:\\杂项\\素材.library\\images\\MMNPVYKJO2R8T.info\\其中包括图片：.png",
    "existing_tags": [],
    "modificationTime": 1773335025091
  }
]